mongosafe/__init__.py
mongosafe-0.0.4.dist-info/DESCRIPTION.rst
mongosafe-0.0.4.dist-info/METADATA
mongosafe-0.0.4.dist-info/RECORD
mongosafe-0.0.4.dist-info/WHEEL
mongosafe-0.0.4.dist-info/metadata.json
mongosafe-0.0.4.dist-info/top_level.txt
