Metadata-Version: 2.0
Name: mongosafe
Version: 0.0.4
Summary: Provides safe reference fields for mongoengine and Flask-admin dashboard.
Home-page: https://github.com/abassel/mongosafe
Author: Alexandre Bassel
Author-email: abassel@gmail.com
License: MIT license
Keywords: mongoengine,Flask-admin,flask
Platform: UNKNOWN
Classifier: Development Status :: 5 - Production/Stable
Classifier: Intended Audience :: Developers
Classifier: License :: OSI Approved :: MIT License
Classifier: Operating System :: Unix
Classifier: Operating System :: POSIX
Classifier: Operating System :: Microsoft :: Windows
Classifier: Programming Language :: Python
Classifier: Programming Language :: Python :: 2.7
Classifier: Programming Language :: Python :: 3
Classifier: Programming Language :: Python :: 3.3
Classifier: Programming Language :: Python :: 3.4
Classifier: Programming Language :: Python :: 3.5
Classifier: Programming Language :: Python :: 3.6
Classifier: Programming Language :: Python :: Implementation :: CPython
Classifier: Programming Language :: Python :: Implementation :: PyPy
Requires-Dist: mongoengine (>=0.15.0)
